[
    {
        "id": "build:(id:2232286),id:1253",
        "name": "org.jetbrains.dukat.compiler.tests.GraalCoreSetTests.withValueSource(String, String, String)[1]",
        "status": "SUCCESS",
        "duration": 14541,
        "href": "/app/rest/testOccurrences/build:(id:2232286),id:1253"
    },
    {
        "id": "build:(id:2232286),id:1259",
        "name": "org.jetbrains.dukat.compiler.tests.GraalCoreSetTests.withValueSource(String, String, String)[2]",
        "status": "SUCCESS",
        "duration": 178,
        "href": "/app/rest/testOccurrences/build:(id:2232286),id:1259"
    },
    {
        "id": "build:(id:2232286),id:1263",
        "name": "org.jetbrains.dukat.compiler.tests.GraalCoreSetTests.withValueSource(String, String, String)[3]",
        "status": "SUCCESS",
        "duration": 125,
        "href": "/app/rest/testOccurrences/build:(id:2232286),id:1263"
    },
    {
        "id": "build:(id:2232286),id:1268",
        "name": "org.jetbrains.dukat.compiler.tests.GraalCoreSetTests.withValueSource(String, String, String)[4]",
        "status": "SUCCESS",
        "duration": 143,
        "href": "/app/rest/testOccurrences/build:(id:2232286),id:1268"
    },
    {
        "id": "build:(id:2232286),id:1273",
        "name": "org.jetbrains.dukat.compiler.tests.GraalCoreSetTests.withValueSource(String, String, String)[5]",
        "status": "SUCCESS",
        "duration": 143,
        "href": "/app/rest/testOccurrences/build:(id:2232286),id:1273"
    },
    {
        "id": "build:(id:2232286),id:1278",
        "name": "org.jetbrains.dukat.compiler.tests.GraalCoreSetTests.withValueSource(String, String, String)[6]",
        "status": "SUCCESS",
        "duration": 139,
        "href": "/app/rest/testOccurrences/build:(id:2232286),id:1278"
    },
    {
        "id": "build:(id:2232286),id:1283",
        "name": "org.jetbrains.dukat.compiler.tests.GraalCoreSetTests.withValueSource(String, String, String)[7]",
        "status": "SUCCESS",
        "duration": 121,
        "href": "/app/rest/testOccurrences/build:(id:2232286),id:1283"
    },
    {
        "id": "build:(id:2232286),id:1288",
        "name": "org.jetbrains.dukat.compiler.tests.GraalCoreSetTests.withValueSource(String, String, String)[8]",
        "status": "SUCCESS",
        "duration": 147,
        "href": "/app/rest/testOccurrences/build:(id:2232286),id:1288"
    },
    {
        "id": "build:(id:2232286),id:1293",
        "name": "org.jetbrains.dukat.compiler.tests.GraalCoreSetTests.withValueSource(String, String, String)[9]",
        "status": "SUCCESS",
        "duration": 85,
        "href": "/app/rest/testOccurrences/build:(id:2232286),id:1293"
    },
    {
        "id": "build:(id:2232286),id:1298",
        "name": "org.jetbrains.dukat.compiler.tests.GraalCoreSetTests.withValueSource(String, String, String)[10]",
        "status": "SUCCESS",
        "duration": 51,
        "href": "/app/rest/testOccurrences/build:(id:2232286),id:1298"
    },
    {
        "id": "build:(id:2232286),id:1302",
        "name": "org.jetbrains.dukat.compiler.tests.GraalCoreSetTests.withValueSource(String, String, String)[11]",
        "status": "SUCCESS",
        "duration": 107,
        "href": "/app/rest/testOccurrences/build:(id:2232286),id:1302"
    },
    {
        "id": "build:(id:2232286),id:1306",
        "name": "org.jetbrains.dukat.compiler.tests.GraalCoreSetTests.withValueSource(String, String, String)[12]",
        "status": "SUCCESS",
        "duration": 87,
        "href": "/app/rest/testOccurrences/build:(id:2232286),id:1306"
    },
    {
        "id": "build:(id:2232286),id:1310",
        "name": "org.jetbrains.dukat.compiler.tests.GraalCoreSetTests.withValueSource(String, String, String)[13]",
        "status": "SUCCESS",
        "duration": 91,
        "href": "/app/rest/testOccurrences/build:(id:2232286),id:1310"
    },
    {
        "id": "build:(id:2232286),id:1314",
        "name": "org.jetbrains.dukat.compiler.tests.GraalCoreSetTests.withValueSource(String, String, String)[14]",
        "status": "SUCCESS",
        "duration": 122,
        "href": "/app/rest/testOccurrences/build:(id:2232286),id:1314"
    },
    {
        "id": "build:(id:2232286),id:1318",
        "name": "org.jetbrains.dukat.compiler.tests.GraalCoreSetTests.withValueSource(String, String, String)[15]",
        "status": "SUCCESS",
        "duration": 62,
        "href": "/app/rest/testOccurrences/build:(id:2232286),id:1318"
    },
    {
        "id": "build:(id:2232286),id:1323",
        "name": "org.jetbrains.dukat.compiler.tests.GraalCoreSetTests.withValueSource(String, String, String)[16]",
        "status": "SUCCESS",
        "duration": 44,
        "href": "/app/rest/testOccurrences/build:(id:2232286),id:1323"
    },
    {
        "id": "build:(id:2232286),id:1327",
        "name": "org.jetbrains.dukat.compiler.tests.GraalCoreSetTests.withValueSource(String, String, String)[17]",
        "status": "SUCCESS",
        "duration": 100,
        "href": "/app/rest/testOccurrences/build:(id:2232286),id:1327"
    },
    {
        "id": "build:(id:2232286),id:1331",
        "name": "org.jetbrains.dukat.compiler.tests.GraalCoreSetTests.withValueSource(String, String, String)[18]",
        "status": "SUCCESS",
        "duration": 56,
        "href": "/app/rest/testOccurrences/build:(id:2232286),id:1331"
    },
    {
        "id": "build:(id:2232286),id:1335",
        "name": "org.jetbrains.dukat.compiler.tests.GraalCoreSetTests.withValueSource(String, String, String)[19]",
        "status": "SUCCESS",
        "duration": 86,
        "href": "/app/rest/testOccurrences/build:(id:2232286),id:1335"
    },
    {
        "id": "build:(id:2232286),id:1339",
        "name": "org.jetbrains.dukat.compiler.tests.GraalCoreSetTests.withValueSource(String, String, String)[20]",
        "status": "SUCCESS",
        "duration": 69,
        "href": "/app/rest/testOccurrences/build:(id:2232286),id:1339"
    },
    {
        "id": "build:(id:2232286),id:1344",
        "name": "org.jetbrains.dukat.compiler.tests.GraalCoreSetTests.withValueSource(String, String, String)[21]",
        "status": "SUCCESS",
        "duration": 64,
        "href": "/app/rest/testOccurrences/build:(id:2232286),id:1344"
    },
    {
        "id": "build:(id:2232286),id:1348",
        "name": "org.jetbrains.dukat.compiler.tests.GraalCoreSetTests.withValueSource(String, String, String)[22]",
        "status": "SUCCESS",
        "duration": 91,
        "href": "/app/rest/testOccurrences/build:(id:2232286),id:1348"
    },
    {
        "id": "build:(id:2232286),id:1353",
        "name": "org.jetbrains.dukat.compiler.tests.GraalCoreSetTests.withValueSource(String, String, String)[23]",
        "status": "SUCCESS",
        "duration": 38,
        "href": "/app/rest/testOccurrences/build:(id:2232286),id:1353"
    },
    {
        "id": "build:(id:2232286),id:1357",
        "name": "org.jetbrains.dukat.compiler.tests.GraalCoreSetTests.withValueSource(String, String, String)[24]",
        "status": "SUCCESS",
        "duration": 122,
        "href": "/app/rest/testOccurrences/build:(id:2232286),id:1357"
    },
    {
        "id": "build:(id:2232286),id:1361",
        "name": "org.jetbrains.dukat.compiler.tests.GraalCoreSetTests.withValueSource(String, String, String)[25]",
        "status": "SUCCESS",
        "duration": 58,
        "href": "/app/rest/testOccurrences/build:(id:2232286),id:1361"
    },
    {
        "id": "build:(id:2232286),id:1365",
        "name": "org.jetbrains.dukat.compiler.tests.GraalCoreSetTests.withValueSource(String, String, String)[26]",
        "status": "SUCCESS",
        "duration": 73,
        "href": "/app/rest/testOccurrences/build:(id:2232286),id:1365"
    },
    {
        "id": "build:(id:2232286),id:1369",
        "name": "org.jetbrains.dukat.compiler.tests.GraalCoreSetTests.withValueSource(String, String, String)[27]",
        "status": "SUCCESS",
        "duration": 83,
        "href": "/app/rest/testOccurrences/build:(id:2232286),id:1369"
    },
    {
        "id": "build:(id:2232286),id:1373",
        "name": "org.jetbrains.dukat.compiler.tests.GraalCoreSetTests.withValueSource(String, String, String)[28]",
        "status": "SUCCESS",
        "duration": 49,
        "href": "/app/rest/testOccurrences/build:(id:2232286),id:1373"
    },
    {
        "id": "build:(id:2232286),id:1377",
        "name": "org.jetbrains.dukat.compiler.tests.GraalCoreSetTests.withValueSource(String, String, String)[29]",
        "status": "SUCCESS",
        "duration": 82,
        "href": "/app/rest/testOccurrences/build:(id:2232286),id:1377"
    },
    {
        "id": "build:(id:2232286),id:1381",
        "name": "org.jetbrains.dukat.compiler.tests.GraalCoreSetTests.withValueSource(String, String, String)[30]",
        "status": "SUCCESS",
        "duration": 44,
        "href": "/app/rest/testOccurrences/build:(id:2232286),id:1381"
    },
    {
        "id": "build:(id:2232286),id:1385",
        "name": "org.jetbrains.dukat.compiler.tests.GraalCoreSetTests.withValueSource(String, String, String)[31]",
        "status": "SUCCESS",
        "duration": 37,
        "href": "/app/rest/testOccurrences/build:(id:2232286),id:1385"
    },
    {
        "id": "build:(id:2232286),id:1389",
        "name": "org.jetbrains.dukat.compiler.tests.GraalCoreSetTests.withValueSource(String, String, String)[32]",
        "status": "SUCCESS",
        "duration": 38,
        "href": "/app/rest/testOccurrences/build:(id:2232286),id:1389"
    },
    {
        "id": "build:(id:2232286),id:1393",
        "name": "org.jetbrains.dukat.compiler.tests.GraalCoreSetTests.withValueSource(String, String, String)[33]",
        "status": "SUCCESS",
        "duration": 40,
        "href": "/app/rest/testOccurrences/build:(id:2232286),id:1393"
    },
    {
        "id": "build:(id:2232286),id:1397",
        "name": "org.jetbrains.dukat.compiler.tests.GraalCoreSetTests.withValueSource(String, String, String)[34]",
        "status": "SUCCESS",
        "duration": 44,
        "href": "/app/rest/testOccurrences/build:(id:2232286),id:1397"
    },
    {
        "id": "build:(id:2232286),id:1401",
        "name": "org.jetbrains.dukat.compiler.tests.GraalCoreSetTests.withValueSource(String, String, String)[35]",
        "status": "SUCCESS",
        "duration": 38,
        "href": "/app/rest/testOccurrences/build:(id:2232286),id:1401"
    },
    {
        "id": "build:(id:2232286),id:1405",
        "name": "org.jetbrains.dukat.compiler.tests.GraalCoreSetTests.withValueSource(String, String, String)[36]",
        "status": "SUCCESS",
        "duration": 43,
        "href": "/app/rest/testOccurrences/build:(id:2232286),id:1405"
    },
    {
        "id": "build:(id:2232286),id:1409",
        "name": "org.jetbrains.dukat.compiler.tests.GraalCoreSetTests.withValueSource(String, String, String)[37]",
        "status": "SUCCESS",
        "duration": 33,
        "href": "/app/rest/testOccurrences/build:(id:2232286),id:1409"
    },
    {
        "id": "build:(id:2232286),id:1413",
        "name": "org.jetbrains.dukat.compiler.tests.GraalCoreSetTests.withValueSource(String, String, String)[38]",
        "status": "SUCCESS",
        "duration": 67,
        "href": "/app/rest/testOccurrences/build:(id:2232286),id:1413"
    },
    {
        "id": "build:(id:2232286),id:1417",
        "name": "org.jetbrains.dukat.compiler.tests.GraalCoreSetTests.withValueSource(String, String, String)[39]",
        "status": "SUCCESS",
        "duration": 49,
        "href": "/app/rest/testOccurrences/build:(id:2232286),id:1417"
    },
    {
        "id": "build:(id:2232286),id:1421",
        "name": "org.jetbrains.dukat.compiler.tests.GraalCoreSetTests.withValueSource(String, String, String)[40]",
        "status": "SUCCESS",
        "duration": 38,
        "href": "/app/rest/testOccurrences/build:(id:2232286),id:1421"
    },
    {
        "id": "build:(id:2232286),id:1425",
        "name": "org.jetbrains.dukat.compiler.tests.GraalCoreSetTests.withValueSource(String, String, String)[41]",
        "status": "SUCCESS",
        "duration": 42,
        "href": "/app/rest/testOccurrences/build:(id:2232286),id:1425"
    },
    {
        "id": "build:(id:2232286),id:1429",
        "name": "org.jetbrains.dukat.compiler.tests.GraalCoreSetTests.withValueSource(String, String, String)[42]",
        "status": "SUCCESS",
        "duration": 182,
        "href": "/app/rest/testOccurrences/build:(id:2232286),id:1429"
    },
    {
        "id": "build:(id:2232286),id:1433",
        "name": "org.jetbrains.dukat.compiler.tests.GraalCoreSetTests.withValueSource(String, String, String)[43]",
        "status": "SUCCESS",
        "duration": 43,
        "href": "/app/rest/testOccurrences/build:(id:2232286),id:1433"
    },
    {
        "id": "build:(id:2232286),id:1437",
        "name": "org.jetbrains.dukat.compiler.tests.GraalCoreSetTests.withValueSource(String, String, String)[44]",
        "status": "SUCCESS",
        "duration": 86,
        "href": "/app/rest/testOccurrences/build:(id:2232286),id:1437"
    },
    {
        "id": "build:(id:2232286),id:1441",
        "name": "org.jetbrains.dukat.compiler.tests.GraalCoreSetTests.withValueSource(String, String, String)[45]",
        "status": "SUCCESS",
        "duration": 195,
        "href": "/app/rest/testOccurrences/build:(id:2232286),id:1441"
    },
    {
        "id": "build:(id:2232286),id:1445",
        "name": "org.jetbrains.dukat.compiler.tests.GraalCoreSetTests.withValueSource(String, String, String)[46]",
        "status": "SUCCESS",
        "duration": 96,
        "href": "/app/rest/testOccurrences/build:(id:2232286),id:1445"
    },
    {
        "id": "build:(id:2232286),id:1449",
        "name": "org.jetbrains.dukat.compiler.tests.GraalCoreSetTests.withValueSource(String, String, String)[47]",
        "status": "SUCCESS",
        "duration": 51,
        "href": "/app/rest/testOccurrences/build:(id:2232286),id:1449"
    },
    {
        "id": "build:(id:2232286),id:1453",
        "name": "org.jetbrains.dukat.compiler.tests.GraalCoreSetTests.withValueSource(String, String, String)[48]",
        "status": "SUCCESS",
        "duration": 118,
        "href": "/app/rest/testOccurrences/build:(id:2232286),id:1453"
    },
    {
        "id": "build:(id:2232286),id:1457",
        "name": "org.jetbrains.dukat.compiler.tests.GraalCoreSetTests.withValueSource(String, String, String)[49]",
        "status": "SUCCESS",
        "duration": 83,
        "href": "/app/rest/testOccurrences/build:(id:2232286),id:1457"
    },
    {
        "id": "build:(id:2232286),id:1461",
        "name": "org.jetbrains.dukat.compiler.tests.GraalCoreSetTests.withValueSource(String, String, String)[50]",
        "status": "SUCCESS",
        "duration": 84,
        "href": "/app/rest/testOccurrences/build:(id:2232286),id:1461"
    },
    {
        "id": "build:(id:2232286),id:1465",
        "name": "org.jetbrains.dukat.compiler.tests.GraalCoreSetTests.withValueSource(String, String, String)[51]",
        "status": "SUCCESS",
        "duration": 81,
        "href": "/app/rest/testOccurrences/build:(id:2232286),id:1465"
    },
    {
        "id": "build:(id:2232286),id:1469",
        "name": "org.jetbrains.dukat.compiler.tests.GraalCoreSetTests.withValueSource(String, String, String)[52]",
        "status": "SUCCESS",
        "duration": 74,
        "href": "/app/rest/testOccurrences/build:(id:2232286),id:1469"
    },
    {
        "id": "build:(id:2232286),id:1473",
        "name": "org.jetbrains.dukat.compiler.tests.GraalCoreSetTests.withValueSource(String, String, String)[53]",
        "status": "SUCCESS",
        "duration": 48,
        "href": "/app/rest/testOccurrences/build:(id:2232286),id:1473"
    },
    {
        "id": "build:(id:2232286),id:1478",
        "name": "org.jetbrains.dukat.compiler.tests.GraalCoreSetTests.withValueSource(String, String, String)[54]",
        "status": "SUCCESS",
        "duration": 44,
        "href": "/app/rest/testOccurrences/build:(id:2232286),id:1478"
    },
    {
        "id": "build:(id:2232286),id:1482",
        "name": "org.jetbrains.dukat.compiler.tests.GraalCoreSetTests.withValueSource(String, String, String)[55]",
        "status": "SUCCESS",
        "duration": 115,
        "href": "/app/rest/testOccurrences/build:(id:2232286),id:1482"
    },
    {
        "id": "build:(id:2232286),id:1486",
        "name": "org.jetbrains.dukat.compiler.tests.GraalCoreSetTests.withValueSource(String, String, String)[56]",
        "status": "SUCCESS",
        "duration": 69,
        "href": "/app/rest/testOccurrences/build:(id:2232286),id:1486"
    },
    {
        "id": "build:(id:2232286),id:1490",
        "name": "org.jetbrains.dukat.compiler.tests.GraalCoreSetTests.withValueSource(String, String, String)[57]",
        "status": "SUCCESS",
        "duration": 49,
        "href": "/app/rest/testOccurrences/build:(id:2232286),id:1490"
    },
    {
        "id": "build:(id:2232286),id:1494",
        "name": "org.jetbrains.dukat.compiler.tests.GraalCoreSetTests.withValueSource(String, String, String)[58]",
        "status": "SUCCESS",
        "duration": 63,
        "href": "/app/rest/testOccurrences/build:(id:2232286),id:1494"
    },
    {
        "id": "build:(id:2232286),id:1498",
        "name": "org.jetbrains.dukat.compiler.tests.GraalCoreSetTests.withValueSource(String, String, String)[59]",
        "status": "SUCCESS",
        "duration": 81,
        "href": "/app/rest/testOccurrences/build:(id:2232286),id:1498"
    },
    {
        "id": "build:(id:2232286),id:1502",
        "name": "org.jetbrains.dukat.compiler.tests.GraalCoreSetTests.withValueSource(String, String, String)[60]",
        "status": "SUCCESS",
        "duration": 147,
        "href": "/app/rest/testOccurrences/build:(id:2232286),id:1502"
    },
    {
        "id": "build:(id:2232286),id:1506",
        "name": "org.jetbrains.dukat.compiler.tests.GraalCoreSetTests.withValueSource(String, String, String)[61]",
        "status": "SUCCESS",
        "duration": 47,
        "href": "/app/rest/testOccurrences/build:(id:2232286),id:1506"
    },
    {
        "id": "build:(id:2232286),id:1510",
        "name": "org.jetbrains.dukat.compiler.tests.GraalCoreSetTests.withValueSource(String, String, String)[62]",
        "status": "SUCCESS",
        "duration": 52,
        "href": "/app/rest/testOccurrences/build:(id:2232286),id:1510"
    },
    {
        "id": "build:(id:2232286),id:1514",
        "name": "org.jetbrains.dukat.compiler.tests.GraalCoreSetTests.withValueSource(String, String, String)[63]",
        "status": "SUCCESS",
        "duration": 66,
        "href": "/app/rest/testOccurrences/build:(id:2232286),id:1514"
    },
    {
        "id": "build:(id:2232286),id:1518",
        "name": "org.jetbrains.dukat.compiler.tests.GraalCoreSetTests.withValueSource(String, String, String)[64]",
        "status": "SUCCESS",
        "duration": 79,
        "href": "/app/rest/testOccurrences/build:(id:2232286),id:1518"
    },
    {
        "id": "build:(id:2232286),id:1522",
        "name": "org.jetbrains.dukat.compiler.tests.GraalCoreSetTests.withValueSource(String, String, String)[65]",
        "status": "SUCCESS",
        "duration": 77,
        "href": "/app/rest/testOccurrences/build:(id:2232286),id:1522"
    },
    {
        "id": "build:(id:2232286),id:1526",
        "name": "org.jetbrains.dukat.compiler.tests.GraalCoreSetTests.withValueSource(String, String, String)[66]",
        "status": "SUCCESS",
        "duration": 113,
        "href": "/app/rest/testOccurrences/build:(id:2232286),id:1526"
    },
    {
        "id": "build:(id:2232286),id:1530",
        "name": "org.jetbrains.dukat.compiler.tests.GraalCoreSetTests.withValueSource(String, String, String)[67]",
        "status": "SUCCESS",
        "duration": 62,
        "href": "/app/rest/testOccurrences/build:(id:2232286),id:1530"
    },
    {
        "id": "build:(id:2232286),id:1534",
        "name": "org.jetbrains.dukat.compiler.tests.GraalCoreSetTests.withValueSource(String, String, String)[68]",
        "status": "SUCCESS",
        "duration": 69,
        "href": "/app/rest/testOccurrences/build:(id:2232286),id:1534"
    },
    {
        "id": "build:(id:2232286),id:1538",
        "name": "org.jetbrains.dukat.compiler.tests.GraalCoreSetTests.withValueSource(String, String, String)[69]",
        "status": "SUCCESS",
        "duration": 71,
        "href": "/app/rest/testOccurrences/build:(id:2232286),id:1538"
    },
    {
        "id": "build:(id:2232286),id:1542",
        "name": "org.jetbrains.dukat.compiler.tests.GraalCoreSetTests.withValueSource(String, String, String)[70]",
        "status": "SUCCESS",
        "duration": 62,
        "href": "/app/rest/testOccurrences/build:(id:2232286),id:1542"
    },
    {
        "id": "build:(id:2232286),id:1546",
        "name": "org.jetbrains.dukat.compiler.tests.GraalCoreSetTests.withValueSource(String, String, String)[71]",
        "status": "SUCCESS",
        "duration": 55,
        "href": "/app/rest/testOccurrences/build:(id:2232286),id:1546"
    },
    {
        "id": "build:(id:2232286),id:1550",
        "name": "org.jetbrains.dukat.compiler.tests.GraalCoreSetTests.withValueSource(String, String, String)[72]",
        "status": "SUCCESS",
        "duration": 73,
        "href": "/app/rest/testOccurrences/build:(id:2232286),id:1550"
    },
    {
        "id": "build:(id:2232286),id:1555",
        "name": "org.jetbrains.dukat.compiler.tests.GraalCoreSetTests.withValueSource(String, String, String)[73]",
        "status": "SUCCESS",
        "duration": 65,
        "href": "/app/rest/testOccurrences/build:(id:2232286),id:1555"
    },
    {
        "id": "build:(id:2232286),id:1559",
        "name": "org.jetbrains.dukat.compiler.tests.GraalCoreSetTests.withValueSource(String, String, String)[74]",
        "status": "SUCCESS",
        "duration": 74,
        "href": "/app/rest/testOccurrences/build:(id:2232286),id:1559"
    },
    {
        "id": "build:(id:2232286),id:1563",
        "name": "org.jetbrains.dukat.compiler.tests.GraalCoreSetTests.withValueSource(String, String, String)[75]",
        "status": "SUCCESS",
        "duration": 33,
        "href": "/app/rest/testOccurrences/build:(id:2232286),id:1563"
    },
    {
        "id": "build:(id:2232286),id:1567",
        "name": "org.jetbrains.dukat.compiler.tests.GraalCoreSetTests.withValueSource(String, String, String)[76]",
        "status": "SUCCESS",
        "duration": 46,
        "href": "/app/rest/testOccurrences/build:(id:2232286),id:1567"
    },
    {
        "id": "build:(id:2232286),id:1572",
        "name": "org.jetbrains.dukat.compiler.tests.GraalCoreSetTests.withValueSource(String, String, String)[77]",
        "status": "SUCCESS",
        "duration": 95,
        "href": "/app/rest/testOccurrences/build:(id:2232286),id:1572"
    },
    {
        "id": "build:(id:2232286),id:1576",
        "name": "org.jetbrains.dukat.compiler.tests.GraalCoreSetTests.withValueSource(String, String, String)[78]",
        "status": "SUCCESS",
        "duration": 88,
        "href": "/app/rest/testOccurrences/build:(id:2232286),id:1576"
    },
    {
        "id": "build:(id:2232286),id:1580",
        "name": "org.jetbrains.dukat.compiler.tests.GraalCoreSetTests.withValueSource(String, String, String)[79]",
        "status": "SUCCESS",
        "duration": 53,
        "href": "/app/rest/testOccurrences/build:(id:2232286),id:1580"
    },
    {
        "id": "build:(id:2232286),id:1584",
        "name": "org.jetbrains.dukat.compiler.tests.GraalCoreSetTests.withValueSource(String, String, String)[80]",
        "status": "SUCCESS",
        "duration": 1078,
        "href": "/app/rest/testOccurrences/build:(id:2232286),id:1584"
    },
    {
        "id": "build:(id:2232286),id:1590",
        "name": "org.jetbrains.dukat.compiler.tests.GraalCoreSetTests.withValueSource(String, String, String)[81]",
        "status": "SUCCESS",
        "duration": 2289,
        "href": "/app/rest/testOccurrences/build:(id:2232286),id:1590"
    },
    {
        "id": "build:(id:2232286),id:1595",
        "name": "org.jetbrains.dukat.compiler.tests.GraalCoreSetTests.withValueSource(String, String, String)[82]",
        "status": "SUCCESS",
        "duration": 46,
        "href": "/app/rest/testOccurrences/build:(id:2232286),id:1595"
    },
    {
        "id": "build:(id:2232286),id:1599",
        "name": "org.jetbrains.dukat.compiler.tests.GraalCoreSetTests.withValueSource(String, String, String)[83]",
        "status": "SUCCESS",
        "duration": 64,
        "href": "/app/rest/testOccurrences/build:(id:2232286),id:1599"
    },
    {
        "id": "build:(id:2232286),id:1603",
        "name": "org.jetbrains.dukat.compiler.tests.GraalCoreSetTests.withValueSource(String, String, String)[84]",
        "status": "SUCCESS",
        "duration": 65,
        "href": "/app/rest/testOccurrences/build:(id:2232286),id:1603"
    },
    {
        "id": "build:(id:2232286),id:1607",
        "name": "org.jetbrains.dukat.compiler.tests.GraalCoreSetTests.withValueSource(String, String, String)[85]",
        "status": "SUCCESS",
        "duration": 54,
        "href": "/app/rest/testOccurrences/build:(id:2232286),id:1607"
    },
    {
        "id": "build:(id:2232286),id:1611",
        "name": "org.jetbrains.dukat.compiler.tests.GraalCoreSetTests.withValueSource(String, String, String)[86]",
        "status": "SUCCESS",
        "duration": 50,
        "href": "/app/rest/testOccurrences/build:(id:2232286),id:1611"
    },
    {
        "id": "build:(id:2232286),id:1615",
        "name": "org.jetbrains.dukat.compiler.tests.GraalCoreSetTests.withValueSource(String, String, String)[87]",
        "status": "SUCCESS",
        "duration": 66,
        "href": "/app/rest/testOccurrences/build:(id:2232286),id:1615"
    },
    {
        "id": "build:(id:2232286),id:1619",
        "name": "org.jetbrains.dukat.compiler.tests.GraalCoreSetTests.withValueSource(String, String, String)[88]",
        "status": "SUCCESS",
        "duration": 42,
        "href": "/app/rest/testOccurrences/build:(id:2232286),id:1619"
    },
    {
        "id": "build:(id:2232286),id:1624",
        "name": "org.jetbrains.dukat.compiler.tests.GraalCoreSetTests.withValueSource(String, String, String)[89]",
        "status": "SUCCESS",
        "duration": 47,
        "href": "/app/rest/testOccurrences/build:(id:2232286),id:1624"
    },
    {
        "id": "build:(id:2232286),id:1628",
        "name": "org.jetbrains.dukat.compiler.tests.GraalCoreSetTests.withValueSource(String, String, String)[90]",
        "status": "SUCCESS",
        "duration": 60,
        "href": "/app/rest/testOccurrences/build:(id:2232286),id:1628"
    },
    {
        "id": "build:(id:2232286),id:1632",
        "name": "org.jetbrains.dukat.compiler.tests.GraalCoreSetTests.withValueSource(String, String, String)[91]",
        "status": "SUCCESS",
        "duration": 35,
        "href": "/app/rest/testOccurrences/build:(id:2232286),id:1632"
    },
    {
        "id": "build:(id:2232286),id:1636",
        "name": "org.jetbrains.dukat.compiler.tests.GraalCoreSetTests.withValueSource(String, String, String)[92]",
        "status": "SUCCESS",
        "duration": 56,
        "href": "/app/rest/testOccurrences/build:(id:2232286),id:1636"
    },
    {
        "id": "build:(id:2232286),id:1640",
        "name": "org.jetbrains.dukat.compiler.tests.GraalCoreSetTests.withValueSource(String, String, String)[93]",
        "status": "SUCCESS",
        "duration": 37,
        "href": "/app/rest/testOccurrences/build:(id:2232286),id:1640"
    },
    {
        "id": "build:(id:2232286),id:1644",
        "name": "org.jetbrains.dukat.compiler.tests.GraalCoreSetTests.withValueSource(String, String, String)[94]",
        "status": "SUCCESS",
        "duration": 58,
        "href": "/app/rest/testOccurrences/build:(id:2232286),id:1644"
    },
    {
        "id": "build:(id:2232286),id:1648",
        "name": "org.jetbrains.dukat.compiler.tests.GraalCoreSetTests.withValueSource(String, String, String)[95]",
        "status": "SUCCESS",
        "duration": 44,
        "href": "/app/rest/testOccurrences/build:(id:2232286),id:1648"
    },
    {
        "id": "build:(id:2232286),id:1652",
        "name": "org.jetbrains.dukat.compiler.tests.GraalCoreSetTests.withValueSource(String, String, String)[96]",
        "status": "SUCCESS",
        "duration": 45,
        "href": "/app/rest/testOccurrences/build:(id:2232286),id:1652"
    },
    {
        "id": "build:(id:2232286),id:1656",
        "name": "org.jetbrains.dukat.compiler.tests.GraalCoreSetTests.withValueSource(String, String, String)[97]",
        "status": "SUCCESS",
        "duration": 96,
        "href": "/app/rest/testOccurrences/build:(id:2232286),id:1656"
    },
    {
        "id": "build:(id:2232286),id:1660",
        "name": "org.jetbrains.dukat.compiler.tests.GraalCoreSetTests.withValueSource(String, String, String)[98]",
        "status": "SUCCESS",
        "duration": 36,
        "href": "/app/rest/testOccurrences/build:(id:2232286),id:1660"
    },
    {
        "id": "build:(id:2232286),id:1664",
        "name": "org.jetbrains.dukat.compiler.tests.GraalCoreSetTests.withValueSource(String, String, String)[99]",
        "status": "SUCCESS",
        "duration": 31,
        "href": "/app/rest/testOccurrences/build:(id:2232286),id:1664"
    },
    {
        "id": "build:(id:2232286),id:1668",
        "name": "org.jetbrains.dukat.compiler.tests.GraalCoreSetTests.withValueSource(String, String, String)[100]",
        "status": "SUCCESS",
        "duration": 97,
        "href": "/app/rest/testOccurrences/build:(id:2232286),id:1668"
    },
    {
        "id": "build:(id:2232286),id:1673",
        "name": "org.jetbrains.dukat.compiler.tests.GraalCoreSetTests.withValueSource(String, String, String)[101]",
        "status": "SUCCESS",
        "duration": 68,
        "href": "/app/rest/testOccurrences/build:(id:2232286),id:1673"
    },
    {
        "id": "build:(id:2232286),id:1677",
        "name": "org.jetbrains.dukat.compiler.tests.GraalCoreSetTests.withValueSource(String, String, String)[102]",
        "status": "SUCCESS",
        "duration": 108,
        "href": "/app/rest/testOccurrences/build:(id:2232286),id:1677"
    },
    {
        "id": "build:(id:2232286),id:1681",
        "name": "org.jetbrains.dukat.compiler.tests.GraalCoreSetTests.withValueSource(String, String, String)[103]",
        "status": "SUCCESS",
        "duration": 89,
        "href": "/app/rest/testOccurrences/build:(id:2232286),id:1681"
    },
    {
        "id": "build:(id:2232286),id:1685",
        "name": "org.jetbrains.dukat.compiler.tests.GraalCoreSetTests.withValueSource(String, String, String)[104]",
        "status": "SUCCESS",
        "duration": 37,
        "href": "/app/rest/testOccurrences/build:(id:2232286),id:1685"
    },
    {
        "id": "build:(id:2232286),id:1689",
        "name": "org.jetbrains.dukat.compiler.tests.GraalCoreSetTests.withValueSource(String, String, String)[105]",
        "status": "SUCCESS",
        "duration": 41,
        "href": "/app/rest/testOccurrences/build:(id:2232286),id:1689"
    },
    {
        "id": "build:(id:2232286),id:1693",
        "name": "org.jetbrains.dukat.compiler.tests.GraalCoreSetTests.withValueSource(String, String, String)[106]",
        "status": "SUCCESS",
        "duration": 45,
        "href": "/app/rest/testOccurrences/build:(id:2232286),id:1693"
    },
    {
        "id": "build:(id:2232286),id:1697",
        "name": "org.jetbrains.dukat.compiler.tests.GraalCoreSetTests.withValueSource(String, String, String)[107]",
        "status": "SUCCESS",
        "duration": 67,
        "href": "/app/rest/testOccurrences/build:(id:2232286),id:1697"
    },
    {
        "id": "build:(id:2232286),id:1701",
        "name": "org.jetbrains.dukat.compiler.tests.GraalCoreSetTests.withValueSource(String, String, String)[108]",
        "status": "SUCCESS",
        "duration": 72,
        "href": "/app/rest/testOccurrences/build:(id:2232286),id:1701"
    },
    {
        "id": "build:(id:2232286),id:1705",
        "name": "org.jetbrains.dukat.compiler.tests.GraalCoreSetTests.withValueSource(String, String, String)[109]",
        "status": "SUCCESS",
        "duration": 80,
        "href": "/app/rest/testOccurrences/build:(id:2232286),id:1705"
    },
    {
        "id": "build:(id:2232286),id:1709",
        "name": "org.jetbrains.dukat.compiler.tests.GraalCoreSetTests.withValueSource(String, String, String)[110]",
        "status": "SUCCESS",
        "duration": 30,
        "href": "/app/rest/testOccurrences/build:(id:2232286),id:1709"
    },
    {
        "id": "build:(id:2232286),id:1713",
        "name": "org.jetbrains.dukat.compiler.tests.GraalCoreSetTests.withValueSource(String, String, String)[111]",
        "status": "SUCCESS",
        "duration": 59,
        "href": "/app/rest/testOccurrences/build:(id:2232286),id:1713"
    },
    {
        "id": "build:(id:2232286),id:1718",
        "name": "org.jetbrains.dukat.compiler.tests.GraalCoreSetTests.withValueSource(String, String, String)[112]",
        "status": "SUCCESS",
        "duration": 40,
        "href": "/app/rest/testOccurrences/build:(id:2232286),id:1718"
    },
    {
        "id": "build:(id:2232286),id:1722",
        "name": "org.jetbrains.dukat.compiler.tests.GraalCoreSetTests.withValueSource(String, String, String)[113]",
        "status": "SUCCESS",
        "duration": 96,
        "href": "/app/rest/testOccurrences/build:(id:2232286),id:1722"
    },
    {
        "id": "build:(id:2232286),id:1726",
        "name": "org.jetbrains.dukat.compiler.tests.GraalCoreSetTests.withValueSource(String, String, String)[114]",
        "status": "SUCCESS",
        "duration": 30,
        "href": "/app/rest/testOccurrences/build:(id:2232286),id:1726"
    },
    {
        "id": "build:(id:2232286),id:1730",
        "name": "org.jetbrains.dukat.compiler.tests.GraalCoreSetTests.withValueSource(String, String, String)[115]",
        "status": "SUCCESS",
        "duration": 27,
        "href": "/app/rest/testOccurrences/build:(id:2232286),id:1730"
    },
    {
        "id": "build:(id:2232286),id:1734",
        "name": "org.jetbrains.dukat.compiler.tests.GraalCoreSetTests.withValueSource(String, String, String)[116]",
        "status": "SUCCESS",
        "duration": 45,
        "href": "/app/rest/testOccurrences/build:(id:2232286),id:1734"
    },
    {
        "id": "build:(id:2232286),id:1738",
        "name": "org.jetbrains.dukat.compiler.tests.GraalCoreSetTests.withValueSource(String, String, String)[117]",
        "status": "SUCCESS",
        "duration": 88,
        "href": "/app/rest/testOccurrences/build:(id:2232286),id:1738"
    },
    {
        "id": "build:(id:2232286),id:1743",
        "name": "org.jetbrains.dukat.compiler.tests.GraalCoreSetTests.withValueSource(String, String, String)[118]",
        "status": "SUCCESS",
        "duration": 205,
        "href": "/app/rest/testOccurrences/build:(id:2232286),id:1743"
    },
    {
        "id": "build:(id:2232286),id:1748",
        "name": "org.jetbrains.dukat.compiler.tests.GraalCoreSetTests.withValueSource(String, String, String)[119]",
        "status": "SUCCESS",
        "duration": 50,
        "href": "/app/rest/testOccurrences/build:(id:2232286),id:1748"
    },
    {
        "id": "build:(id:2232286),id:1752",
        "name": "org.jetbrains.dukat.compiler.tests.GraalCoreSetTests.withValueSource(String, String, String)[120]",
        "status": "SUCCESS",
        "duration": 41,
        "href": "/app/rest/testOccurrences/build:(id:2232286),id:1752"
    },
    {
        "id": "build:(id:2232286),id:1756",
        "name": "org.jetbrains.dukat.compiler.tests.GraalCoreSetTests.withValueSource(String, String, String)[121]",
        "status": "SUCCESS",
        "duration": 51,
        "href": "/app/rest/testOccurrences/build:(id:2232286),id:1756"
    },
    {
        "id": "build:(id:2232286),id:1760",
        "name": "org.jetbrains.dukat.compiler.tests.GraalCoreSetTests.withValueSource(String, String, String)[122]",
        "status": "SUCCESS",
        "duration": 61,
        "href": "/app/rest/testOccurrences/build:(id:2232286),id:1760"
    },
    {
        "id": "build:(id:2232286),id:1764",
        "name": "org.jetbrains.dukat.compiler.tests.GraalCoreSetTests.withValueSource(String, String, String)[123]",
        "status": "SUCCESS",
        "duration": 86,
        "href": "/app/rest/testOccurrences/build:(id:2232286),id:1764"
    },
    {
        "id": "build:(id:2232286),id:1768",
        "name": "org.jetbrains.dukat.compiler.tests.GraalCoreSetTests.withValueSource(String, String, String)[124]",
        "status": "SUCCESS",
        "duration": 21,
        "href": "/app/rest/testOccurrences/build:(id:2232286),id:1768"
    },
    {
        "id": "build:(id:2232286),id:1772",
        "name": "org.jetbrains.dukat.compiler.tests.GraalCoreSetTests.withValueSource(String, String, String)[125]",
        "status": "SUCCESS",
        "duration": 24,
        "href": "/app/rest/testOccurrences/build:(id:2232286),id:1772"
    },
    {
        "id": "build:(id:2232286),id:1776",
        "name": "org.jetbrains.dukat.compiler.tests.GraalCoreSetTests.withValueSource(String, String, String)[126]",
        "status": "SUCCESS",
        "duration": 25,
        "href": "/app/rest/testOccurrences/build:(id:2232286),id:1776"
    },
    {
        "id": "build:(id:2232286),id:1780",
        "name": "org.jetbrains.dukat.compiler.tests.GraalCoreSetTests.withValueSource(String, String, String)[127]",
        "status": "SUCCESS",
        "duration": 19,
        "href": "/app/rest/testOccurrences/build:(id:2232286),id:1780"
    },
    {
        "id": "build:(id:2232286),id:1784",
        "name": "org.jetbrains.dukat.compiler.tests.GraalCoreSetTests.withValueSource(String, String, String)[128]",
        "status": "SUCCESS",
        "duration": 32,
        "href": "/app/rest/testOccurrences/build:(id:2232286),id:1784"
    },
    {
        "id": "build:(id:2232286),id:1788",
        "name": "org.jetbrains.dukat.compiler.tests.GraalCoreSetTests.withValueSource(String, String, String)[129]",
        "status": "SUCCESS",
        "duration": 32,
        "href": "/app/rest/testOccurrences/build:(id:2232286),id:1788"
    },
    {
        "id": "build:(id:2232286),id:1792",
        "name": "org.jetbrains.dukat.compiler.tests.GraalCoreSetTests.withValueSource(String, String, String)[130]",
        "status": "SUCCESS",
        "duration": 57,
        "href": "/app/rest/testOccurrences/build:(id:2232286),id:1792"
    },
    {
        "id": "build:(id:2232286),id:1796",
        "name": "org.jetbrains.dukat.compiler.tests.GraalCoreSetTests.withValueSource(String, String, String)[131]",
        "status": "SUCCESS",
        "duration": 32,
        "href": "/app/rest/testOccurrences/build:(id:2232286),id:1796"
    },
    {
        "id": "build:(id:2232286),id:1800",
        "name": "org.jetbrains.dukat.compiler.tests.GraalCoreSetTests.withValueSource(String, String, String)[132]",
        "status": "SUCCESS",
        "duration": 86,
        "href": "/app/rest/testOccurrences/build:(id:2232286),id:1800"
    },
    {
        "id": "build:(id:2232286),id:1804",
        "name": "org.jetbrains.dukat.compiler.tests.GraalCoreSetTests.withValueSource(String, String, String)[133]",
        "status": "SUCCESS",
        "duration": 22,
        "href": "/app/rest/testOccurrences/build:(id:2232286),id:1804"
    },
    {
        "id": "build:(id:2232286),id:1808",
        "name": "org.jetbrains.dukat.compiler.tests.GraalCoreSetTests.withValueSource(String, String, String)[134]",
        "status": "SUCCESS",
        "duration": 43,
        "href": "/app/rest/testOccurrences/build:(id:2232286),id:1808"
    },
    {
        "id": "build:(id:2232286),id:1812",
        "name": "org.jetbrains.dukat.compiler.tests.GraalCoreSetTests.withValueSource(String, String, String)[135]",
        "status": "SUCCESS",
        "duration": 25,
        "href": "/app/rest/testOccurrences/build:(id:2232286),id:1812"
    },
    {
        "id": "build:(id:2232286),id:1817",
        "name": "org.jetbrains.dukat.compiler.tests.GraalCoreSetTests.withValueSource(String, String, String)[136]",
        "status": "SUCCESS",
        "duration": 33,
        "href": "/app/rest/testOccurrences/build:(id:2232286),id:1817"
    },
    {
        "id": "build:(id:2232286),id:1821",
        "name": "org.jetbrains.dukat.compiler.tests.GraalCoreSetTests.withValueSource(String, String, String)[137]",
        "status": "SUCCESS",
        "duration": 30,
        "href": "/app/rest/testOccurrences/build:(id:2232286),id:1821"
    },
    {
        "id": "build:(id:2232286),id:1825",
        "name": "org.jetbrains.dukat.compiler.tests.GraalCoreSetTests.withValueSource(String, String, String)[138]",
        "status": "SUCCESS",
        "duration": 21,
        "href": "/app/rest/testOccurrences/build:(id:2232286),id:1825"
    },
    {
        "id": "build:(id:2232286),id:1829",
        "name": "org.jetbrains.dukat.compiler.tests.GraalCoreSetTests.withValueSource(String, String, String)[139]",
        "status": "SUCCESS",
        "duration": 41,
        "href": "/app/rest/testOccurrences/build:(id:2232286),id:1829"
    },
    {
        "id": "build:(id:2232286),id:1833",
        "name": "org.jetbrains.dukat.compiler.tests.GraalCoreSetTests.withValueSource(String, String, String)[140]",
        "status": "SUCCESS",
        "duration": 21,
        "href": "/app/rest/testOccurrences/build:(id:2232286),id:1833"
    },
    {
        "id": "build:(id:2232286),id:1837",
        "name": "org.jetbrains.dukat.compiler.tests.GraalCoreSetTests.withValueSource(String, String, String)[141]",
        "status": "SUCCESS",
        "duration": 25,
        "href": "/app/rest/testOccurrences/build:(id:2232286),id:1837"
    },
    {
        "id": "build:(id:2232286),id:1841",
        "name": "org.jetbrains.dukat.compiler.tests.GraalCoreSetTests.withValueSource(String, String, String)[142]",
        "status": "SUCCESS",
        "duration": 28,
        "href": "/app/rest/testOccurrences/build:(id:2232286),id:1841"
    },
    {
        "id": "build:(id:2232286),id:1845",
        "name": "org.jetbrains.dukat.compiler.tests.GraalCoreSetTests.withValueSource(String, String, String)[143]",
        "status": "SUCCESS",
        "duration": 28,
        "href": "/app/rest/testOccurrences/build:(id:2232286),id:1845"
    },
    {
        "id": "build:(id:2232286),id:1849",
        "name": "org.jetbrains.dukat.compiler.tests.GraalCoreSetTests.withValueSource(String, String, String)[144]",
        "status": "SUCCESS",
        "duration": 52,
        "href": "/app/rest/testOccurrences/build:(id:2232286),id:1849"
    },
    {
        "id": "build:(id:2232286),id:1853",
        "name": "org.jetbrains.dukat.compiler.tests.GraalCoreSetTests.withValueSource(String, String, String)[145]",
        "status": "SUCCESS",
        "duration": 59,
        "href": "/app/rest/testOccurrences/build:(id:2232286),id:1853"
    },
    {
        "id": "build:(id:2232286),id:1857",
        "name": "org.jetbrains.dukat.compiler.tests.GraalCoreSetTests.withValueSource(String, String, String)[146]",
        "status": "SUCCESS",
        "duration": 27,
        "href": "/app/rest/testOccurrences/build:(id:2232286),id:1857"
    },
    {
        "id": "build:(id:2232286),id:1861",
        "name": "org.jetbrains.dukat.compiler.tests.GraalCoreSetTests.withValueSource(String, String, String)[147]",
        "status": "SUCCESS",
        "duration": 30,
        "href": "/app/rest/testOccurrences/build:(id:2232286),id:1861"
    },
    {
        "id": "build:(id:2232286),id:1865",
        "name": "org.jetbrains.dukat.compiler.tests.GraalCoreSetTests.withValueSource(String, String, String)[148]",
        "status": "SUCCESS",
        "duration": 64,
        "href": "/app/rest/testOccurrences/build:(id:2232286),id:1865"
    },
    {
        "id": "build:(id:2232286),id:1869",
        "name": "org.jetbrains.dukat.compiler.tests.GraalCoreSetTests.withValueSource(String, String, String)[149]",
        "status": "SUCCESS",
        "duration": 43,
        "href": "/app/rest/testOccurrences/build:(id:2232286),id:1869"
    },
    {
        "id": "build:(id:2232286),id:1873",
        "name": "org.jetbrains.dukat.compiler.tests.GraalCoreSetTests.withValueSource(String, String, String)[150]",
        "status": "SUCCESS",
        "duration": 33,
        "href": "/app/rest/testOccurrences/build:(id:2232286),id:1873"
    },
    {
        "id": "build:(id:2232286),id:1877",
        "name": "org.jetbrains.dukat.compiler.tests.GraalCoreSetTests.withValueSource(String, String, String)[151]",
        "status": "SUCCESS",
        "duration": 75,
        "href": "/app/rest/testOccurrences/build:(id:2232286),id:1877"
    },
    {
        "id": "build:(id:2232286),id:1881",
        "name": "org.jetbrains.dukat.compiler.tests.GraalCoreSetTests.withValueSource(String, String, String)[152]",
        "status": "SUCCESS",
        "duration": 24,
        "href": "/app/rest/testOccurrences/build:(id:2232286),id:1881"
    },
    {
        "id": "build:(id:2232286),id:1886",
        "name": "org.jetbrains.dukat.compiler.tests.GraalCoreSetTests.withValueSource(String, String, String)[153]",
        "status": "SUCCESS",
        "duration": 38,
        "href": "/app/rest/testOccurrences/build:(id:2232286),id:1886"
    },
    {
        "id": "build:(id:2232286),id:1891",
        "name": "org.jetbrains.dukat.compiler.tests.GraalCoreSetTests.withValueSource(String, String, String)[154]",
        "status": "SUCCESS",
        "duration": 54,
        "href": "/app/rest/testOccurrences/build:(id:2232286),id:1891"
    },
    {
        "id": "build:(id:2232286),id:1895",
        "name": "org.jetbrains.dukat.compiler.tests.GraalCoreSetTests.withValueSource(String, String, String)[155]",
        "status": "SUCCESS",
        "duration": 145,
        "href": "/app/rest/testOccurrences/build:(id:2232286),id:1895"
    },
    {
        "id": "build:(id:2232286),id:1899",
        "name": "org.jetbrains.dukat.compiler.tests.GraalCoreSetTests.withValueSource(String, String, String)[156]",
        "status": "SUCCESS",
        "duration": 46,
        "href": "/app/rest/testOccurrences/build:(id:2232286),id:1899"
    },
    {
        "id": "build:(id:2232286),id:1903",
        "name": "org.jetbrains.dukat.compiler.tests.GraalCoreSetTests.withValueSource(String, String, String)[157]",
        "status": "SUCCESS",
        "duration": 42,
        "href": "/app/rest/testOccurrences/build:(id:2232286),id:1903"
    },
    {
        "id": "build:(id:2232286),id:1907",
        "name": "org.jetbrains.dukat.compiler.tests.GraalCoreSetTests.withValueSource(String, String, String)[158]",
        "status": "SUCCESS",
        "duration": 65,
        "href": "/app/rest/testOccurrences/build:(id:2232286),id:1907"
    },
    {
        "id": "build:(id:2232286),id:1911",
        "name": "org.jetbrains.dukat.compiler.tests.GraalCoreSetTests.withValueSource(String, String, String)[159]",
        "status": "SUCCESS",
        "duration": 43,
        "href": "/app/rest/testOccurrences/build:(id:2232286),id:1911"
    },
    {
        "id": "build:(id:2232286),id:1915",
        "name": "org.jetbrains.dukat.compiler.tests.GraalCoreSetTests.withValueSource(String, String, String)[160]",
        "status": "SUCCESS",
        "duration": 30,
        "href": "/app/rest/testOccurrences/build:(id:2232286),id:1915"
    },
    {
        "id": "build:(id:2232286),id:1919",
        "name": "org.jetbrains.dukat.compiler.tests.GraalCoreSetTests.withValueSource(String, String, String)[161]",
        "status": "SUCCESS",
        "duration": 28,
        "href": "/app/rest/testOccurrences/build:(id:2232286),id:1919"
    },
    {
        "id": "build:(id:2232286),id:2032",
        "name": "org.jetbrains.dukat.itertools.tests.ItertoolsTests.singleWithMultiple",
        "status": "SUCCESS",
        "duration": 45,
        "href": "/app/rest/testOccurrences/build:(id:2232286),id:2032"
    },
    {
        "id": "build:(id:2232286),id:2036",
        "name": "org.jetbrains.dukat.itertools.tests.ItertoolsTests.cartesianEmptyList",
        "status": "SUCCESS",
        "duration": 14,
        "href": "/app/rest/testOccurrences/build:(id:2232286),id:2036"
    },
    {
        "id": "build:(id:2232286),id:2040",
        "name": "org.jetbrains.dukat.itertools.tests.ItertoolsTests.multipleLists",
        "status": "SUCCESS",
        "duration": 4,
        "href": "/app/rest/testOccurrences/build:(id:2232286),id:2040"
    },
    {
        "id": "build:(id:2232286),id:2044",
        "name": "org.jetbrains.dukat.itertools.tests.ItertoolsTests.twoMultipleElementLists",
        "status": "SUCCESS",
        "duration": 3,
        "href": "/app/rest/testOccurrences/build:(id:2232286),id:2044"
    },
    {
        "id": "build:(id:2232286),id:2048",
        "name": "org.jetbrains.dukat.itertools.tests.ItertoolsTests.multipleSingleLists",
        "status": "SUCCESS",
        "duration": 1,
        "href": "/app/rest/testOccurrences/build:(id:2232286),id:2048"
    },
    {
        "id": "build:(id:2232286),id:2052",
        "name": "org.jetbrains.dukat.itertools.tests.ItertoolsTests.twoLists",
        "status": "SUCCESS",
        "duration": 1,
        "href": "/app/rest/testOccurrences/build:(id:2232286),id:2052"
    },
    {
        "id": "build:(id:2232286),id:2056",
        "name": "org.jetbrains.dukat.itertools.tests.ItertoolsTests.singleElementList",
        "status": "SUCCESS",
        "duration": 1,
        "href": "/app/rest/testOccurrences/build:(id:2232286),id:2056"
    }
]